CHANGES
MANIFEST.in
README.rst
setup.py
hsaudiotag/__init__.py
hsaudiotag/aiff.py
hsaudiotag/auto.py
hsaudiotag/flac.py
hsaudiotag/genres.py
hsaudiotag/id3v1.py
hsaudiotag/id3v2.py
hsaudiotag/mp4.py
hsaudiotag/mpeg.py
hsaudiotag/ogg.py
hsaudiotag/util.py
hsaudiotag/wma.py
hsaudiotag3k.egg-info/PKG-INFO
hsaudiotag3k.egg-info/SOURCES.txt
hsaudiotag3k.egg-info/dependency_links.txt
hsaudiotag3k.egg-info/top_level.txt