Metadata-Version: 1.1
Name: hsaudiotag3k
Version: 1.1.3.post1
Summary: Read metdata (tags) of mp3, mp4, wma, ogg, flac and aiff files.
Home-page: http://hg.hardcoded.net/hsaudiotag/
Author: Hardcoded Software
Author-email: hsoft@hardcoded.net
License: BSD License
Platform: UNKNOWN
Classifier: Development Status :: 5 - Production/Stable
Classifier: Intended Audience :: Developers
Classifier: License :: OSI Approved :: BSD License
Classifier: Programming Language :: Python :: 3
